Workbook

Sheet README
A1: Enactus Evidence Tracker — Fliq / Enactus HKUST
A3: Impact window (edit these two cells — everything filters on them)
A4: Window start | B4: 46266
A5: Window end | B5: 46630
A7: How to use | B7: Log every beneficiary, session, dollar and mention in the sheets as it happens — not at competition time. The Summary sheet computes the Standardized Impact Page numbers from these rows automatically; only rows inside the impact window count.
A8: Yellow cells | B8: The only cells you edit on this sheet (the window dates).
A9: Gray italic rows | B9: Example rows showing the expected format — replace them with real data.
A10: Direct impact rule | B10: A beneficiary counts as Direct Impact only if Type = Direct AND both Pre and Post scores are recorded (measured change, per Enactus definitions).
A11: Reach rule | B11: Downloads, waitlist, media and event exposure are Reach — never report them as impact.
A12: Income rule | B12: Only Sales / Grant / Sponsorship / Donation with Direction = Income count as Income/Revenue. Log equity investment with Direction = Excluded so it can never leak into the table.
A13: Review readiness | B13: Keep receipt/consent/evidence links filled: the Impact & Financial Reporting Review may contact beneficiaries and ask for documents. Numbers freeze one month before the World Cup.

Sheet Beneficiaries
A1: ID | B1: Name | C1: Project | D1: Type | E1: School / Channel | F1: Consent (Y/N) | G1: Contact | H1: Date engaged | I1: Pre score | J1: Post score | K1: Improvement % | L1: Measured direct? | M1: In window? | N1: Notes
A2: B-001 | B2: Chan Tai Man | C2: Decode: Veritas | D2: Direct | E2: SKH Secondary School | F2: Y | G2: teacher@school.edu.hk | H2: 46309 | I2: 55 | J2: 82 | K2: =IF(AND(ISNUMBER(I2),ISNUMBER(J2),I2>0),(J2-I2)/I2,"") -> 0.49090909 | L2: =IF(A2="","",IF(AND(D2="Direct",ISNUMBER(I2),ISNUMBER(J2)),"Yes","No")) -> Yes | M2: =IF(H2="","",IF(AND(H2>=README!$B$4,H2<=README!$B$5),"Yes","No")) -> Yes | N2: EXAMPLE ROW — replace. Pre/post = media-literacy test scores.
K3: =IF(AND(ISNUMBER(I3),ISNUMBER(J3),I3>0),(J3-I3)/I3,"") | L3: =IF(A3="","",IF(AND(D3="Direct",ISNUMBER(I3),ISNUMBER(J3)),"Yes","No")) | M3: =IF(H3="","",IF(AND(H3>=README!$B$4,H3<=README!$B$5),"Yes","No"))
K4: =IF(AND(ISNUMBER(I4),ISNUMBER(J4),I4>0),(J4-I4)/I4,"") | L4: =IF(A4="","",IF(AND(D4="Direct",ISNUMBER(I4),ISNUMBER(J4)),"Yes","No")) | M4: =IF(H4="","",IF(AND(H4>=README!$B$4,H4<=README!$B$5),"Yes","No"))
K5: =IF(AND(ISNUMBER(I5),ISNUMBER(J5),I5>0),(J5-I5)/I5,"") | L5: =IF(A5="","",IF(AND(D5="Direct",ISNUMBER(I5),ISNUMBER(J5)),"Yes","No")) | M5: =IF(H5="","",IF(AND(H5>=README!$B$4,H5<=README!$B$5),"Yes","No"))
K6: =IF(AND(ISNUMBER(I6),ISNUMBER(J6),I6>0),(J6-I6)/I6,"") | L6: =IF(A6="","",IF(AND(D6="Direct",ISNUMBER(I6),ISNUMBER(J6)),"Yes","No")) | M6: =IF(H6="","",IF(AND(H6>=README!$B$4,H6<=README!$B$5),"Yes","No"))
K7: =IF(AND(ISNUMBER(I7),ISNUMBER(J7),I7>0),(J7-I7)/I7,"") | L7: =IF(A7="","",IF(AND(D7="Direct",ISNUMBER(I7),ISNUMBER(J7)),"Yes","No")) | M7: =IF(H7="","",IF(AND(H7>=README!$B$4,H7<=README!$B$5),"Yes","No"))
K8: =IF(AND(ISNUMBER(I8),ISNUMBER(J8),I8>0),(J8-I8)/I8,"") | L8: =IF(A8="","",IF(AND(D8="Direct",ISNUMBER(I8),ISNUMBER(J8)),"Yes","No")) | M8: =IF(H8="","",IF(AND(H8>=README!$B$4,H8<=README!$B$5),"Yes","No"))
K9: =IF(AND(ISNUMBER(I9),ISNUMBER(J9),I9>0),(J9-I9)/I9,"") | L9: =IF(A9="","",IF(AND(D9="Direct",ISNUMBER(I9),ISNUMBER(J9)),"Yes","No")) | M9: =IF(H9="","",IF(AND(H9>=README!$B$4,H9<=README!$B$5),"Yes","No"))
K10: =IF(AND(ISNUMBER(I10),ISNUMBER(J10),I10>0),(J10-I10)/I10,"") | L10: =IF(A10="","",IF(AND(D10="Direct",ISNUMBER(I10),ISNUMBER(J10)),"Yes","No")) | M10: =IF(H10="","",IF(AND(H10>=README!$B$4,H10<=README!$B$5),"Yes","No"))
K11: =IF(AND(ISNUMBER(I11),ISNUMBER(J11),I11>0),(J11-I11)/I11,"") | L11: =IF(A11="","",IF(AND(D11="Direct",ISNUMBER(I11),ISNUMBER(J11)),"Yes","No")) | M11: =IF(H11="","",IF(AND(H11>=README!$B$4,H11<=README!$B$5),"Yes","No"))
K12: =IF(AND(ISNUMBER(I12),ISNUMBER(J12),I12>0),(J12-I12)/I12,"") | L12: =IF(A12="","",IF(AND(D12="Direct",ISNUMBER(I12),ISNUMBER(J12)),"Yes","No")) | M12: =IF(H12="","",IF(AND(H12>=README!$B$4,H12<=README!$B$5),"Yes","No"))
K13: =IF(AND(ISNUMBER(I13),ISNUMBER(J13),I13>0),(J13-I13)/I13,"") | L13: =IF(A13="","",IF(AND(D13="Direct",ISNUMBER(I13),ISNUMBER(J13)),"Yes","No")) | M13: =IF(H13="","",IF(AND(H13>=README!$B$4,H13<=README!$B$5),"Yes","No"))
K14: =IF(AND(ISNUMBER(I14),ISNUMBER(J14),I14>0),(J14-I14)/I14,"") | L14: =IF(A14="","",IF(AND(D14="Direct",ISNUMBER(I14),ISNUMBER(J14)),"Yes","No")) | M14: =IF(H14="","",IF(AND(H14>=README!$B$4,H14<=README!$B$5),"Yes","No"))
... K201: =IF(AND(ISNUMBER(I201),ISNUMBER(J201),I201>0),(J201-I201)/I201,"") | L201: =IF(A201="","",IF(AND(D201="Direct",ISNUMBER(I201),ISNUMBER(J201)),"Yes","No")) | M201: =IF(H201="","",IF(AND(H201>=README!$B$4,H201<=README!$B$5),"Yes","No"))

Sheet Sessions
A1: Date | B1: Project | C1: School / Venue | D1: Session topic | E1: Attendees | F1: Facilitator (team member) | G1: Evidence link (register/photos) | H1: In window?
A2: 46309 | B2: Decode: Veritas | C2: SKH Secondary School | D2: Claims vs evidence workshop | E2: 32 | F2: Ling Bo Zeng | G2: drive.google.com/… | H2: =IF(A2="","",IF(AND(A2>=README!$B$4,A2<=README!$B$5),"Yes","No")) -> Yes
H3: =IF(A3="","",IF(AND(A3>=README!$B$4,A3<=README!$B$5),"Yes","No"))
H4: =IF(A4="","",IF(AND(A4>=README!$B$4,A4<=README!$B$5),"Yes","No"))
H5: =IF(A5="","",IF(AND(A5>=README!$B$4,A5<=README!$B$5),"Yes","No"))
H6: =IF(A6="","",IF(AND(A6>=README!$B$4,A6<=README!$B$5),"Yes","No"))
H7: =IF(A7="","",IF(AND(A7>=README!$B$4,A7<=README!$B$5),"Yes","No"))
H8: =IF(A8="","",IF(AND(A8>=README!$B$4,A8<=README!$B$5),"Yes","No"))
H9: =IF(A9="","",IF(AND(A9>=README!$B$4,A9<=README!$B$5),"Yes","No"))
H10: =IF(A10="","",IF(AND(A10>=README!$B$4,A10<=README!$B$5),"Yes","No"))
H11: =IF(A11="","",IF(AND(A11>=README!$B$4,A11<=README!$B$5),"Yes","No"))
H12: =IF(A12="","",IF(AND(A12>=README!$B$4,A12<=README!$B$5),"Yes","No"))
H13: =IF(A13="","",IF(AND(A13>=README!$B$4,A13<=README!$B$5),"Yes","No"))
H14: =IF(A14="","",IF(AND(A14>=README!$B$4,A14<=README!$B$5),"Yes","No"))
... H201: =IF(A201="","",IF(AND(A201>=README!$B$4,A201<=README!$B$5),"Yes","No"))

Sheet Revenue
A1: Date | B1: Project | C1: Direction | D1: Type | E1: Description | F1: Amount (USD) | G1: Receipt / doc ref | H1: In window?
A2: 46328 | B2: Fliq | C2: Income | D2: Sales | E2: EXAMPLE — App subscriptions, November | F2: 120 | G2: stripe-2026-11.pdf | H2: =IF(A2="","",IF(AND(A2>=README!$B$4,A2<=README!$B$5),"Yes","No")) -> Yes
A3: 46346 | B3: Decode: Veritas | C3: Income | D3: Sales | E3: EXAMPLE — School programme fee | F3: 250 | G3: invoice-DV-003.pdf | H3: =IF(A3="","",IF(AND(A3>=README!$B$4,A3<=README!$B$5),"Yes","No")) -> Yes
A4: 46357 | B4: Fliq | C4: Excluded | D4: Investment (excluded) | E4: EXAMPLE — Angel round tranche (never in the table) | F4: 10000 | G4: sha-2026.pdf | H4: =IF(A4="","",IF(AND(A4>=README!$B$4,A4<=README!$B$5),"Yes","No")) -> Yes
A5: 46356 | B5: Fliq | C5: Expense | D5: Infrastructure | E5: EXAMPLE — Cloud + licensed sourcing | F5: 310 | G5: aws-2026-11.pdf | H5: =IF(A5="","",IF(AND(A5>=README!$B$4,A5<=README!$B$5),"Yes","No")) -> Yes
H6: =IF(A6="","",IF(AND(A6>=README!$B$4,A6<=README!$B$5),"Yes","No"))
H7: =IF(A7="","",IF(AND(A7>=README!$B$4,A7<=README!$B$5),"Yes","No"))
H8: =IF(A8="","",IF(AND(A8>=README!$B$4,A8<=README!$B$5),"Yes","No"))
H9: =IF(A9="","",IF(AND(A9>=README!$B$4,A9<=README!$B$5),"Yes","No"))
H10: =IF(A10="","",IF(AND(A10>=README!$B$4,A10<=README!$B$5),"Yes","No"))
H11: =IF(A11="","",IF(AND(A11>=README!$B$4,A11<=README!$B$5),"Yes","No"))
H12: =IF(A12="","",IF(AND(A12>=README!$B$4,A12<=README!$B$5),"Yes","No"))
H13: =IF(A13="","",IF(AND(A13>=README!$B$4,A13<=README!$B$5),"Yes","No"))
H14: =IF(A14="","",IF(AND(A14>=README!$B$4,A14<=README!$B$5),"Yes","No"))
H15: =IF(A15="","",IF(AND(A15>=README!$B$4,A15<=README!$B$5),"Yes","No"))
H16: =IF(A16="","",IF(AND(A16>=README!$B$4,A16<=README!$B$5),"Yes","No"))
H17: =IF(A17="","",IF(AND(A17>=README!$B$4,A17<=README!$B$5),"Yes","No"))
... H201: =IF(A201="","",IF(AND(A201>=README!$B$4,A201<=README!$B$5),"Yes","No"))

Sheet Partners
A1: Partner | B1: Role in project | C1: What the partner provided | D1: What the team itself did | E1: Contact | F1: Agreement / doc ref
A2: SKH Secondary School | B2: Host school | C2: Classroom access, student cohort | D2: EXAMPLE — All curriculum design, teaching and testing by team | E2: vice-principal@school.edu.hk | F2: mou-skh.pdf

Sheet ReachLog
A1: Date | B1: Project | C1: Channel | D1: Count (people) | E1: Evidence link | F1: In window?
A2: 46341 | B2: Fliq | C2: App downloads (cumulative delta) | D2: 480 | E2: appstoreconnect screenshot | F2: =IF(A2="","",IF(AND(A2>=README!$B$4,A2<=README!$B$5),"Yes","No")) -> Yes
F3: =IF(A3="","",IF(AND(A3>=README!$B$4,A3<=README!$B$5),"Yes","No"))
F4: =IF(A4="","",IF(AND(A4>=README!$B$4,A4<=README!$B$5),"Yes","No"))
F5: =IF(A5="","",IF(AND(A5>=README!$B$4,A5<=README!$B$5),"Yes","No"))
F6: =IF(A6="","",IF(AND(A6>=README!$B$4,A6<=README!$B$5),"Yes","No"))
F7: =IF(A7="","",IF(AND(A7>=README!$B$4,A7<=README!$B$5),"Yes","No"))
F8: =IF(A8="","",IF(AND(A8>=README!$B$4,A8<=README!$B$5),"Yes","No"))
F9: =IF(A9="","",IF(AND(A9>=README!$B$4,A9<=README!$B$5),"Yes","No"))
F10: =IF(A10="","",IF(AND(A10>=README!$B$4,A10<=README!$B$5),"Yes","No"))
F11: =IF(A11="","",IF(AND(A11>=README!$B$4,A11<=README!$B$5),"Yes","No"))
F12: =IF(A12="","",IF(AND(A12>=README!$B$4,A12<=README!$B$5),"Yes","No"))
F13: =IF(A13="","",IF(AND(A13>=README!$B$4,A13<=README!$B$5),"Yes","No"))
F14: =IF(A14="","",IF(AND(A14>=README!$B$4,A14<=README!$B$5),"Yes","No"))
... F201: =IF(A201="","",IF(AND(A201>=README!$B$4,A201<=README!$B$5),"Yes","No"))

Sheet Summary
A1: Standardized Impact Page — computed from the raw sheets (copy these numbers to the report only after deleting example rows)
A2: Project | B2: Direct Impact (people) | C2: Indirect Impact (people) | D2: Reach (people) | E2: Income/Revenue (USD) | F2: Expenses (USD) | G2: Profit/Surplus (USD) | H2: Avg score improvement
A3: Decode: Veritas | B3: =COUNTIFS(Beneficiaries!C:C,$A3,Beneficiaries!L:L,"Yes",Beneficiaries!M:M,"Yes") -> 1 | C3: =COUNTIFS(Beneficiaries!C:C,$A3,Beneficiaries!D:D,"Indirect",Beneficiaries!M:M,"Yes") -> 0 | D3: =SUMIFS(ReachLog!D:D,ReachLog!B:B,$A3,ReachLog!F:F,"Yes") -> 0 | E3: =SUMIFS(Revenue!F:F,Revenue!B:B,$A3,Revenue!C:C,"Income",Revenue!H:H,"Yes") -> 250 | F3: =SUMIFS(Revenue!F:F,Revenue!B:B,$A3,Revenue!C:C,"Expense",Revenue!H:H,"Yes") -> 0 | G3: =E3-F3 -> 250 | H3: =IFERROR(AVERAGEIFS(Beneficiaries!K:K,Beneficiaries!C:C,$A3,Beneficiaries!L:L,"Yes",Beneficiaries!M:M,"Yes"),"") -> 0.49090909
A4: Fliq | B4: =COUNTIFS(Beneficiaries!C:C,$A4,Beneficiaries!L:L,"Yes",Beneficiaries!M:M,"Yes") -> 0 | C4: =COUNTIFS(Beneficiaries!C:C,$A4,Beneficiaries!D:D,"Indirect",Beneficiaries!M:M,"Yes") -> 0 | D4: =SUMIFS(ReachLog!D:D,ReachLog!B:B,$A4,ReachLog!F:F,"Yes") -> 480 | E4: =SUMIFS(Revenue!F:F,Revenue!B:B,$A4,Revenue!C:C,"Income",Revenue!H:H,"Yes") -> 120 | F4: =SUMIFS(Revenue!F:F,Revenue!B:B,$A4,Revenue!C:C,"Expense",Revenue!H:H,"Yes") -> 310 | G4: =E4-F4 -> -190 | H4: =IFERROR(AVERAGEIFS(Beneficiaries!K:K,Beneficiaries!C:C,$A4,Beneficiaries!L:L,"Yes",Beneficiaries!M:M,"Yes"),"")
A5: Other | B5: =COUNTIFS(Beneficiaries!C:C,$A5,Beneficiaries!L:L,"Yes",Beneficiaries!M:M,"Yes") -> 0 | C5: =COUNTIFS(Beneficiaries!C:C,$A5,Beneficiaries!D:D,"Indirect",Beneficiaries!M:M,"Yes") -> 0 | D5: =SUMIFS(ReachLog!D:D,ReachLog!B:B,$A5,ReachLog!F:F,"Yes") -> 0 | E5: =SUMIFS(Revenue!F:F,Revenue!B:B,$A5,Revenue!C:C,"Income",Revenue!H:H,"Yes") -> 0 | F5: =SUMIFS(Revenue!F:F,Revenue!B:B,$A5,Revenue!C:C,"Expense",Revenue!H:H,"Yes") -> 0 | G5: =E5-F5 -> 0 | H5: =IFERROR(AVERAGEIFS(Beneficiaries!K:K,Beneficiaries!C:C,$A5,Beneficiaries!L:L,"Yes",Beneficiaries!M:M,"Yes"),"")
A6: Total | B6: =SUM(B3:B5) -> 1 | C6: =SUM(C3:C5) -> 0 | D6: =SUM(D3:D5) -> 480 | E6: =SUM(E3:E5) -> 370 | F6: =SUM(F3:F5) -> 310 | G6: =SUM(G3:G5) -> 60
A8: Note: 'Other' rows come from any additional Enactus HKUST projects logged with Project = Other. Copy the totals into the Standardized Impact Page; the two must always match.
